agentstack/__init__.py
agentstack/agents.py
agentstack/auth.py
agentstack/conf.py
agentstack/exceptions.py
agentstack/graph.py
agentstack/inputs.py
agentstack/log.py
agentstack/main.py
agentstack/packaging.py
agentstack/providers.py
agentstack/repo.py
agentstack/tasks.py
agentstack/telemetry.py
agentstack/update.py
agentstack/utils.py
agentstack/_tools/__init__.py
agentstack/_tools/example_config.json
agentstack/_tools/agent_connect/__init__.py
agentstack/_tools/agent_connect/config.json
agentstack/_tools/agentmail/__init__.py
agentstack/_tools/agentmail/config.json
agentstack/_tools/agentql/__init__.py
agentstack/_tools/agentql/config.json
agentstack/_tools/browserbase/__init__.py
agentstack/_tools/browserbase/config.json
agentstack/_tools/code_interpreter/Dockerfile
agentstack/_tools/code_interpreter/__init__.py
agentstack/_tools/code_interpreter/config.json
agentstack/_tools/composio/__init__.py
agentstack/_tools/composio/config.json
agentstack/_tools/dappier/__init__.py
agentstack/_tools/dappier/config.json
agentstack/_tools/directory_search/__init__.py
agentstack/_tools/directory_search/config.json
agentstack/_tools/exa/__init__.py
agentstack/_tools/exa/config.json
agentstack/_tools/file_read/__init__.py
agentstack/_tools/file_read/config.json
agentstack/_tools/firecrawl/__init__.py
agentstack/_tools/firecrawl/config.json
agentstack/_tools/ftp/__init__.py
agentstack/_tools/ftp/config.json
agentstack/_tools/hyperbrowser/__init__.py
agentstack/_tools/hyperbrowser/config.json
agentstack/_tools/hyperspell/__init__.py
agentstack/_tools/hyperspell/config.json
agentstack/_tools/mem0/__init__.py
agentstack/_tools/mem0/config.json
agentstack/_tools/neon/__init__.py
agentstack/_tools/neon/config.json
agentstack/_tools/open_interpreter/__init__.py
agentstack/_tools/open_interpreter/config.json
agentstack/_tools/payman/__init__.py
agentstack/_tools/payman/config.json
agentstack/_tools/perplexity/__init__.py
agentstack/_tools/perplexity/config.json
agentstack-0.3.7.dist-info/licenses/LICENSE
agentstack-0.3.7.dist-info/METADATA
agentstack-0.3.7.dist-info/WHEEL
agentstack-0.3.7.dist-info/entry_points.txt
agentstack-0.3.7.dist-info/top_level.txt
agentstack-0.3.7.dist-info/RECORD
