Metadata-Version: 2.4
Name: agentstack
Version: 0.3.7
Summary: The fastest way to build robust AI agents
Author-email: Braelyn Boynton <bboynton97@gmail.com>, Travis Dent <root@a10k.co>
License: MIT
Requires-Python: >=3.10
License-File: LICENSE
Requires-Dist: agentops>=0.4.9
Requires-Dist: typer>=0.12.5
Requires-Dist: inquirer>=3.4.0
Requires-Dist: art>=6.3
Requires-Dist: toml>=0.10.2
Requires-Dist: ruamel.yaml.base>=0.3.2
Requires-Dist: cookiecutter==2.6.0
Requires-Dist: psutil==5.9.8
Requires-Dist: astor==0.8.1
Requires-Dist: asttokens
Requires-Dist: pydantic>=2.10
Requires-Dist: packaging>=23.2
Requires-Dist: requests>=2.32
Requires-Dist: appdirs>=1.4.4
Requires-Dist: python-dotenv>=1.0.1
Requires-Dist: uv>=0.5.6
Requires-Dist: tomli>=2.2.1
Requires-Dist: gitpython>=3.1.44
Provides-Extra: dev
Requires-Dist: mypy>=1.13.0; extra == "dev"
Requires-Dist: pre-commit>=4.0.1; extra == "dev"
Requires-Dist: ruff>=0.8.2; extra == "dev"
Provides-Extra: test
Requires-Dist: tox; extra == "test"
Provides-Extra: crewai
Requires-Dist: crewai==0.118.0; extra == "crewai"
Requires-Dist: crewai-tools==0.33.0; extra == "crewai"
Requires-Dist: shapely==2.0.6; extra == "crewai"
Provides-Extra: langgraph
Requires-Dist: langgraph>=0.2.61; extra == "langgraph"
Requires-Dist: langchain>=0.3.14; extra == "langgraph"
Provides-Extra: openai-swarm
Requires-Dist: agentstack-openai-swarm>=0.0.1; extra == "openai-swarm"
Provides-Extra: llamaindex
Requires-Dist: llama-index-core>=0.12.16; extra == "llamaindex"
Dynamic: license-file
